{
  "": "",
  "Javascript- язык программироваия!": "",
  "Profile page": "",
  "error": "",
  "throw error": "",
  "Ваш ": "",
  "Ваш автар": "",
  "Ваш возраст": "",
  "Ваш город": "",
  "Ваша фамилия": "",
  "Ваше имя": "",
  "Введите имя пользователя": "",
  "Введите имя пользователя ": "",
  "Введите логин": "",
  "Введите пароль": "",
  "Введите ссылку на аватар": "",
  "Войти": "",
  "Вы ввели неверный логин или пароль": "",
  "Выйти": "",
  "Главная": "",
  "Главная,jh": "",
  "Город": "",
  "Данные не указаны": "",
  "Имя и фамилия обязательные поля": "",
  "Некорректная страна": "",
  "Некорректное имя": "",
  "Некорректный возраст": "",
  "О сайте": "",
  "О те": "",
  "Обновить страницу": "",
  "Отмена": "",
  "Ошибка сервера": "",
  "Ошибка сервера при сохранении": "",
  "Попробуйте обновить страницу!": "",
  "Произошла непредвиденная ошибка": "",
  "Произошла ошибка": "",
  "Произошла ошибка при загрузке пользователя!": "",
  "Произошла ошибка при загрузке статьи!": "",
  "Профиль": "",
  "Профиль пользователя": "",
  "Редактировать": "",
  "Сохранить": "",
  "Статья не найдена": "",
  "Страница не найдена": "",
  "Укажите алюту": "",
  "Укажите валюту": "",
  "Укажите страну": "",
  "Форма авторизации": "",
  "Язык": "",
  "страница": "",
  "страница ид": ""
}
